odoo/addons/partner_risk_insurance/README.rst
odoo/addons/partner_risk_insurance/__init__.py
odoo/addons/partner_risk_insurance/__manifest__.py
odoo/addons/partner_risk_insurance/i18n/ca.po
odoo/addons/partner_risk_insurance/i18n/es.po
odoo/addons/partner_risk_insurance/i18n/es_ES.po
odoo/addons/partner_risk_insurance/i18n/partner_risk_insurance.pot
odoo/addons/partner_risk_insurance/i18n/pt.po
odoo/addons/partner_risk_insurance/i18n/pt_BR.po
odoo/addons/partner_risk_insurance/i18n/sl.po
odoo/addons/partner_risk_insurance/models/__init__.py
odoo/addons/partner_risk_insurance/models/credit_policy.py
odoo/addons/partner_risk_insurance/models/res_partner.py
odoo/addons/partner_risk_insurance/readme/CONTRIBUTORS.rst
odoo/addons/partner_risk_insurance/readme/DESCRIPTION.rst
odoo/addons/partner_risk_insurance/readme/USAGE.rst
odoo/addons/partner_risk_insurance/security/ir.model.access.csv
odoo/addons/partner_risk_insurance/static/description/icon.png
odoo/addons/partner_risk_insurance/static/description/index.html
odoo/addons/partner_risk_insurance/tests/__init__.py
odoo/addons/partner_risk_insurance/tests/test_partner_risk_insurance.py
odoo/addons/partner_risk_insurance/views/res_partner_view.xml
odoo13_addon_partner_risk_insurance-13.0.1.2.0.dist-info/METADATA
odoo13_addon_partner_risk_insurance-13.0.1.2.0.dist-info/WHEEL
odoo13_addon_partner_risk_insurance-13.0.1.2.0.dist-info/top_level.txt
odoo13_addon_partner_risk_insurance-13.0.1.2.0.dist-info/RECORD
