Metadata-Version: 2.1
Name: odoo13-addon-partner-risk-insurance
Version: 13.0.1.2.0
Summary: Risk insurance partner information
Home-page: https://github.com/OCA/credit-control
Author: AvanzOSC,Tecnativa,Factor Libre S.L,NaN·tic,Odoo Community Association (OCA)
Author-email: support@odoo-community.org
License: AGPL-3
Platform: UNKNOWN
Classifier: Programming Language :: Python
Classifier: Framework :: Odoo
Classifier: Framework :: Odoo :: 13.0
Classifier: License :: OSI Approved :: GNU Affero General Public License v3
Classifier: Development Status :: 5 - Production/Stable
Requires-Python: >=3.5
Requires-Dist: odoo (<13.1dev,>=13.0a)
